BookOnTypescript/README.md
BookOnTypescript/__init__.py
BookOnTypescript/__main__.py
BookOnTypescript/file.epub
BookOnTypescript/index.html
BookOnTypescript/css/__init__.py
BookOnTypescript/css/annotations.css
BookOnTypescript/css/main.css
BookOnTypescript/css/normalize.css
BookOnTypescript/css/popup.css
BookOnTypescript/font/__init__.py
BookOnTypescript/font/fontello.eot
BookOnTypescript/font/fontello.svg
BookOnTypescript/font/fontello.ttf
BookOnTypescript/font/fontello.woff
BookOnTypescript/img/__init__.py
BookOnTypescript/img/annotator-glyph-sprite.png
BookOnTypescript/img/annotator-icon-sprite.png
BookOnTypescript/img/apple-touch-icon.png
BookOnTypescript/img/cancelfullscreen.png
BookOnTypescript/img/close.png
BookOnTypescript/img/fullscreen.png
BookOnTypescript/img/loader.gif
BookOnTypescript/img/menu-icon.png
BookOnTypescript/img/save.png
BookOnTypescript/img/saved.png
BookOnTypescript/img/settings-s.png
BookOnTypescript/img/settings.png
BookOnTypescript/img/star.png
BookOnTypescript/js/__init__.py
BookOnTypescript/js/epub.js
BookOnTypescript/js/epub.min.js
BookOnTypescript/js/epub.min.map
BookOnTypescript/js/hooks.min.js
BookOnTypescript/js/hooks.min.map
BookOnTypescript/js/reader.js
BookOnTypescript/js/reader.js.map
BookOnTypescript/js/reader.min.js
BookOnTypescript/js/reader.min.map
BookOnTypescript/js/hooks/__init__.py
BookOnTypescript/js/hooks/extensions/__init__.py
BookOnTypescript/js/hooks/extensions/highlight.js
BookOnTypescript/js/libs/__init__.py
BookOnTypescript/js/libs/jquery.min.js
BookOnTypescript/js/libs/localforage.min.js
BookOnTypescript/js/libs/screenfull.js
BookOnTypescript/js/libs/screenfull.min.js
BookOnTypescript/js/libs/zip.min.js
BookOnTypescript/js/plugins/__init__.py
BookOnTypescript/js/plugins/hypothesis.js
BookOnTypescript/js/plugins/search.js
book_on_typescript-2024.3.4.0.dist-info/METADATA
book_on_typescript-2024.3.4.0.dist-info/WHEEL
book_on_typescript-2024.3.4.0.dist-info/entry_points.txt
book_on_typescript-2024.3.4.0.dist-info/top_level.txt
book_on_typescript-2024.3.4.0.dist-info/RECORD
